bs_common_fastapi/__init__.py
bs_common_fastapi/common/__init__.py
bs_common_fastapi/common/config/__init__.py
bs_common_fastapi/common/config/base.py
bs_common_fastapi/common/dependency/__init__.py
bs_common_fastapi/common/dependency/base.py
bs_common_fastapi/common/exception/__init__.py
bs_common_fastapi/common/model/__init__.py
bs_common_fastapi/common/model/base_default_model.py
bs_common_fastapi-0.3.3.dist-info/METADATA
bs_common_fastapi-0.3.3.dist-info/WHEEL
bs_common_fastapi-0.3.3.dist-info/RECORD
