Metadata-Version: 2.1
Name: bs-common-fastapi
Version: 0.3.3
Summary: 
Author: Bruno Segato
Author-email: brunosegatoit@gmail.com
Requires-Python: >=3.11,<4.0
Classifier: Programming Language :: Python :: 3
Classifier: Programming Language :: Python :: 3.11
Requires-Dist: fastapi (>=0.97.0,<0.98.0)
